LICENSE
README.md
setup.py
lib/__init__.py
lib/history_set.py
lib/history_set.egg-info/PKG-INFO
lib/history_set.egg-info/SOURCES.txt
lib/history_set.egg-info/dependency_links.txt
lib/history_set.egg-info/top_level.txt