Metadata-Version: 2.1
Name: history-set
Version: 0.3.0
Summary: A Set implementation that tracks added and removed elements.
Home-page: https://bitbucket.org/westmont/history_set
Author: Dave Lundgren, Connor Riva, Tjaart van der Walt
Author-email: dlungren@outsideopen.com, criva@westmont.edu, tjaart@outsideopen.com
License: UNKNOWN
Platform: UNKNOWN
Classifier: Development Status :: 3 - Alpha
Classifier: Intended Audience :: Developers
Classifier: License :: OSI Approved :: MIT License
Classifier: Programming Language :: Python :: 2
Classifier: Programming Language :: Python :: 3
License-File: LICENSE
